{
  "prip" : {
    "mappings" : {
      "properties" : {
        "attr_beginningDateTime_date" : {
          "type" : "date"
        },
        "attr_completionTimeFromAscendingNode_double" : {
          "type" : "float"
        },
        "attr_coordinates_string" : {
          "type" : "text",
          "fields" : {
            "keyword" : {
              "type" : "keyword",
              "ignore_above" : 256
            }
          }
        },
        "attr_cycleNumber_long" : {
          "type" : "long"
        },
        "attr_endingDateTime_date" : {
          "type" : "date"
        },
        "attr_instrumentConfigurationID_string" : {
          "type" : "text",
          "fields" : {
            "keyword" : {
              "type" : "keyword",
              "ignore_above" : 256
            }
          }
        },
        "attr_instrumentShortName_string" : {
          "type" : "text",
          "fields" : {
            "keyword" : {
              "type" : "keyword",
              "ignore_above" : 256
            }
          }
        },
        "attr_missionDatatakeID_long" : {
          "type" : "long"
        },
        "attr_orbitDirection_string" : {
          "type" : "text",
          "fields" : {
            "keyword" : {
              "type" : "keyword",
              "ignore_above" : 256
            }
          }
        },
        "attr_orbitNumber_long" : {
          "type" : "long"
        },
        "attr_platformSerialIdentifier_string" : {
          "type" : "text",
          "fields" : {
            "keyword" : {
              "type" : "keyword",
              "ignore_above" : 256
            }
          }
        },
        "attr_platformShortName_string" : {
          "type" : "text",
          "fields" : {
            "keyword" : {
              "type" : "keyword",
              "ignore_above" : 256
            }
          }
        },
        "attr_polarisationChannels_string" : {
          "type" : "text",
          "fields" : {
            "keyword" : {
              "type" : "keyword",
              "ignore_above" : 256
            }
          }
        },
        "attr_processingCenter_string" : {
          "type" : "text",
          "fields" : {
            "keyword" : {
              "type" : "keyword",
              "ignore_above" : 256
            }
          }
        },
        "attr_processingDate_date" : {
          "type" : "date"
        },
        "attr_processorVersion_string" : {
          "type" : "text",
          "fields" : {
            "keyword" : {
              "type" : "keyword",
              "ignore_above" : 256
            }
          }
        },
        "attr_productClass_string" : {
          "type" : "text",
          "fields" : {
            "keyword" : {
              "type" : "keyword",
              "ignore_above" : 256
            }
          }
        },
        "attr_productConsolidation_string" : {
          "type" : "text",
          "fields" : {
            "keyword" : {
              "type" : "keyword",
              "ignore_above" : 256
            }
          }
        },
        "attr_productGeneration_date" : {
          "type" : "date"
        },
        "attr_productType_string" : {
          "type" : "text",
          "fields" : {
            "keyword" : {
              "type" : "keyword",
              "ignore_above" : 256
            }
          }
        },
        "attr_relativeOrbitNumber_long" : {
          "type" : "long"
        },
        "attr_sliceNumber_long" : {
          "type" : "long"
        },
        "attr_startTimeFromAscendingNode_double" : {
          "type" : "float"
        },
        "attr_totalSlices_long" : {
          "type" : "long"
        },
        "checksum" : {
          "type" : "nested",
          "properties" : {
            "algorithm" : {
              "type" : "keyword"
            },
            "checksum_date" : {
              "type" : "date"
            },
            "value" : {
              "type" : "keyword"
            }
          }
        },
        "contentDateEnd" : {
          "type" : "date"
        },
        "contentDateStart" : {
          "type" : "date"
        },
        "contentLength" : {
          "type" : "long"
        },
        "contentType" : {
          "type" : "keyword"
        },
        "creationDate" : {
          "type" : "date"
        },
        "evictionDate" : {
          "type" : "date"
        },
        "footprint" : {
          "type" : "geo_shape",
          "strategy" : "recursive",
          "tree" : "geohash"
        },
        "id" : {
          "type" : "keyword"
        },
        "name" : {
          "type" : "keyword"
        },
        "obsKey" : {
          "type" : "keyword"
        },
        "productFamily" : {
          "type" : "keyword"
        }
      }
    }
  }
}
